trakt_watch/__init__.py
trakt_watch/__main__.py
trakt_watch/core.py
trakt_watch/py.typed
trakt_watch-0.1.2.dist-info/LICENSE
trakt_watch-0.1.2.dist-info/METADATA
trakt_watch-0.1.2.dist-info/WHEEL
trakt_watch-0.1.2.dist-info/entry_points.txt
trakt_watch-0.1.2.dist-info/top_level.txt
trakt_watch-0.1.2.dist-info/RECORD
