Metadata-Version: 2.1
Name: trakt_watch
Version: 0.1.2
Summary: a small CLI to mark items watched on trakt
Home-page: https://github.com/purarue/trakt-watch
Author: purarue
License: MIT
Classifier: License :: OSI Approved :: MIT License
Classifier: Programming Language :: Python
Classifier: Programming Language :: Python :: 3
Classifier: Programming Language :: Python :: 3 :: Only
Classifier: Programming Language :: Python :: 3.11
Classifier: Programming Language :: Python :: 3.12
Classifier: Programming Language :: Python :: 3.13
Requires-Python: >=3.11
License-File: LICENSE
Requires-Dist: click>=8.1.6
Requires-Dist: dateparser
Requires-Dist: pytrakt>=3.4.30
Requires-Dist: traktexport>=0.1.8
Provides-Extra: testing
Requires-Dist: flake8; extra == "testing"
Requires-Dist: mypy; extra == "testing"
